polywrap_sys_config_bundle/__init__.py
polywrap_sys_config_bundle/bundle.py
polywrap_sys_config_bundle/embeds/__init__.py
polywrap_sys_config_bundle/embeds/embedded_file_reader.py
polywrap_sys_config_bundle/embeds/file-system-resolver/wrap.info
polywrap_sys_config_bundle/embeds/file-system-resolver/wrap.wasm
polywrap_sys_config_bundle/embeds/http-resolver/wrap.info
polywrap_sys_config_bundle/embeds/http-resolver/wrap.wasm
polywrap_sys_config_bundle/embeds/ipfs-http-client/wrap.info
polywrap_sys_config_bundle/embeds/ipfs-http-client/wrap.wasm
polywrap_sys_config_bundle/embeds/ipfs-sync-resolver/wrap.info
polywrap_sys_config_bundle/embeds/ipfs-sync-resolver/wrap.wasm
polywrap_sys_config_bundle/py.typed
polywrap_sys_config_bundle-0.1.2.dist-info/METADATA
polywrap_sys_config_bundle-0.1.2.dist-info/WHEEL
polywrap_sys_config_bundle-0.1.2.dist-info/RECORD
