Metadata-Version: 2.1
Name: polywrap-sys-config-bundle
Version: 0.1.2
Summary: Polywrap System Client Config Bundle
Author: Niraj
Author-email: niraj@polywrap.io
Requires-Python: >=3.10,<4.0
Classifier: Programming Language :: Python :: 3
Classifier: Programming Language :: Python :: 3.10
Classifier: Programming Language :: Python :: 3.11
Requires-Dist: polywrap-client-config-builder (==0.1.2)
Requires-Dist: polywrap-core (==0.1.2)
Requires-Dist: polywrap-fs-plugin (==0.1.2)
Requires-Dist: polywrap-http-plugin (==0.1.2)
Requires-Dist: polywrap-manifest (==0.1.2)
Requires-Dist: polywrap-uri-resolvers (==0.1.2)
Requires-Dist: polywrap-wasm (==0.1.2)
